pyaging/__init__.py
pyaging/data/__init__.py
pyaging/data/_data.py
pyaging/logger/__init__.py
pyaging/logger/_logger.py
pyaging/models/__init__.py
pyaging/models/_base_models.py
pyaging/models/_models.py
pyaging/predict/__init__.py
pyaging/predict/_postprocessing.py
pyaging/predict/_pred.py
pyaging/predict/_pred_utils.py
pyaging/predict/_preprocessing.py
pyaging/preprocess/__init__.py
pyaging/preprocess/_preprocess.py
pyaging/preprocess/_preprocess_utils.py
pyaging/utils/__init__.py
pyaging/utils/_utils.py
pyaging-0.1.30.dist-info/METADATA
pyaging-0.1.30.dist-info/WHEEL
pyaging-0.1.30.dist-info/entry_points.txt
pyaging-0.1.30.dist-info/licenses/LICENSE
pyaging-0.1.30.dist-info/RECORD
