Metadata-Version: 2.4
Name: pyaging
Version: 0.1.30
Summary: A Python-based compendium of GPU-optimized aging clocks.
Project-URL: homepage, https://github.com/rsinghlab/pyaging
Project-URL: repository, https://github.com/rsinghlab/pyaging
Author-email: Lucas Paulo de Lima Camillo <lucas_camillo@alumni.brown.edu>
License: BSD
License-File: LICENSE
Requires-Python: <3.14,>=3.9
Requires-Dist: anndata>=0.10.3
Requires-Dist: ipykernel>=6.29.0
Requires-Dist: marimo[recommended]>=0.17.6
Requires-Dist: matplotlib>=3.9.4
Requires-Dist: numpy>=2.0.0
Requires-Dist: openai>=2.8.1
Requires-Dist: pandas>=2.2.0
Requires-Dist: plotly>=6.5.0
Requires-Dist: polars>=1.35.2
Requires-Dist: pyarrow>=21.0.0
Requires-Dist: requests
Requires-Dist: ruff>=0.14.6
Requires-Dist: scikit-learn>=1.3.2
Requires-Dist: torch>=2.2.0
Requires-Dist: tox>=4.30.3
Provides-Extra: docs
Requires-Dist: ipykernel>=6.29.0; extra == 'docs'
Requires-Dist: nbsphinx>=0.8.11; extra == 'docs'
Requires-Dist: pygments>=2.6.1; extra == 'docs'
Requires-Dist: sphinx-autodoc-typehints>=1.12.0; extra == 'docs'
Requires-Dist: sphinx-rtd-theme>=1.3.0rc1; extra == 'docs'
Requires-Dist: sphinx>=7.1.2; extra == 'docs'
Provides-Extra: histone
Requires-Dist: pybigwig>=0.3.23; extra == 'histone'
